CHANGES.rst
COPYING.txt
MANIFEST.in
README.rst
setup.py
configurator/__init__.py
configurator/convertor.py
configurator/formats/__init__.py
configurator/formats/_safe_importer.py
configurator/formats/json.py
configurator/formats/pickle.py
configurator/formats/python.py
configurator/formats/__pycache__/__init__.cpython-35.pyc
configurator/formats/__pycache__/_safe_importer.cpython-35.pyc
configurator/formats/__pycache__/json.cpython-35.pyc
configurator/formats/__pycache__/python.cpython-35.pyc
configurator/testing/source.py
configurator/testing/source.py.json
configurator/testing/source.py.pickle
configurator/testing/source.py.python
python_configurator.egg-info/PKG-INFO
python_configurator.egg-info/SOURCES.txt
python_configurator.egg-info/dependency_links.txt
python_configurator.egg-info/top_level.txt