Metadata-Version: 1.1
Name: python-configurator
Version: 0.3
Summary: Python module for reading configuration files in different formats
Home-page: https://github.com/HugoShamrock/python-configurator
Author: Hugo Shamrock
Author-email: hugo.shamrock@gmail.com
License: UNKNOWN
Platform: UNKNOWN
Classifier: Programming Language :: Python :: 3
Classifier: Programming Language :: Python
Classifier: License :: OSI Approved :: GNU General Public License v3 or later (GPLv3+)
Classifier: Operating System :: OS Independent
Classifier: Development Status :: 5 - Production/Stable
Classifier: Intended Audience :: Developers
Classifier: Topic :: Software Development
